<?xml version="1.0"?>
  <database name="MODIFIED TABLE C_INVOICETAX">
    <table name="C_INVOICETAX" primaryKey="C_INVOICETAX_KEY">
      <column name="EM_SCO_SPECIALDOCTYPE" primaryKey="false" required="false" type="VARCHAR" size="60" autoIncrement="false">
        <default/>
        <onCreateDefault/>
      </column>
      <column name="EM_SCO_AUTOGENERATED" primaryKey="false" required="false" type="CHAR" size="1" autoIncrement="false">
        <default><![CDATA[N]]></default>
        <onCreateDefault/>
      </column>
      <check name="EM_SCO_INVTAX_AGEN_CHK"><![CDATA[EM_SCO_AUTOGENERATED IN ('Y', 'N')]]></check>
    </table>
  </database>
