<?xml version="1.0"?>
  <database name="MODIFIED TABLE M_INOUTLINE">
    <table name="M_INOUTLINE" primaryKey="M_INOUTLINE_KEY">
      <column name="EM_SWA_NUM_CAJAS_PERLINE" primaryKey="false" required="false" type="DECIMAL" autoIncrement="false">
        <default><![CDATA[0]]></default>
        <onCreateDefault/>
      </column>
      <column name="EM_SWA_PESO_PERLINE" primaryKey="false" required="false" type="DECIMAL" autoIncrement="false">
        <default><![CDATA[0]]></default>
        <onCreateDefault/>
      </column>
      <column name="EM_SWA_NUMCAJASINT_PERLINE" primaryKey="false" required="false" type="DECIMAL" autoIncrement="false">
        <default><![CDATA[0]]></default>
        <onCreateDefault/>
      </column>
      <column name="EM_SWA_CUBICAJE_PERLINE" primaryKey="false" required="false" type="DECIMAL" autoIncrement="false">
        <default><![CDATA[0]]></default>
        <onCreateDefault/>
      </column>
      <column name="EM_SWA_CAJASEXTRAS_PERLINE" primaryKey="false" required="false" type="DECIMAL" autoIncrement="false">
        <default><![CDATA[0]]></default>
        <onCreateDefault/>
      </column>
      <column name="EM_SWA_CUBICAJEEXTRA_PERLINE" primaryKey="false" required="false" type="DECIMAL" autoIncrement="false">
        <default><![CDATA[0]]></default>
        <onCreateDefault/>
      </column>
      <column name="EM_SWA_PREFERREDDIM_ID" primaryKey="false" required="false" type="VARCHAR" size="32" autoIncrement="false">
        <default/>
        <onCreateDefault/>
      </column>
      <column name="EM_SWA_REQUEREPO_DETAIL_ID" primaryKey="false" required="false" type="VARCHAR" size="32" autoIncrement="false">
        <default/>
        <onCreateDefault/>
      </column>
      <column name="EM_SWA_CREATELINES_PURCHORDER" primaryKey="false" required="false" type="CHAR" size="1" autoIncrement="false">
        <default/>
        <onCreateDefault/>
      </column>
      <column name="EM_SWA_STATUS_PICKING_LINE" primaryKey="false" required="false" type="VARCHAR" size="60" autoIncrement="false">
        <default><![CDATA[PD]]></default>
        <onCreateDefault/>
      </column>
      <foreign-key foreignTable="SWA_PREFERREDDIMENSION" name="EM_SWA_PREFERREDDIM_FK">
        <reference local="EM_SWA_PREFERREDDIM_ID" foreign="SWA_PREFERREDDIMENSION_ID"/>
      </foreign-key>
      <foreign-key foreignTable="SWA_REQUEREPO_DETAIL" name="EM_SWA_REPOREQUEDETAIL_FK">
        <reference local="EM_SWA_REQUEREPO_DETAIL_ID" foreign="SWA_REQUEREPO_DETAIL_ID"/>
      </foreign-key>
    </table>
  </database>
