<?xml version="1.0" encoding="UTF-8" standalone="no"?>
<compiereTrl baseLanguage="en_US" language="es_PE" table="AD_FIELD" version="">
  <row id="07704D7F8EC54861B176ACC4F0803A47" trl="Y">
    <value column="Name" isTrl="Y" original="Default Role">Rol por defecto</value>
    <value column="Description" isTrl="N" original="Defines the default role used when creating a new user">Defines the default role used when creating a new user</value>
    <value column="Help" isTrl="N" original="Defines the default role used when the process of login in with a Google Account doesn't find any Openbravo user associated with the account.">Defines the default role used when the process of login in with a Google Account doesn't find any Openbravo user associated with the account.</value>
  </row>
</compiereTrl>
