<?xml version="1.0" encoding="UTF-8" standalone="no"?>
<compiereTrl baseLanguage="en_US" language="es_PE" table="AD_PROCESS" version="">
  <row id="FF8081813383F2CD0133840D04680012" trl="N">
    <value column="Name" isTrl="N" original="PrintOrdersBPLanguageProcess">PrintOrdersBPLanguageProcess</value>
    <value column="Description" isTrl="Y" original="Print Orders BP Language">Imprime Pedidos en el Lenguaje del Tercero</value>
    <value column="Help" isTrl="N" original=""/>
  </row>
  <row id="FF808181339321290133935D82980070" trl="N">
    <value column="Name" isTrl="N" original="PrintInvoicesBPLanguageProcess">PrintInvoicesBPLanguageProcess</value>
    <value column="Description" isTrl="Y" original="Print Invoices BP Language Process">Imprime Facturas en el Lenguaje del Tercero</value>
    <value column="Help" isTrl="N" original=""/>
  </row>
  <row id="FF808181339321290133936E66F400B4" trl="N">
    <value column="Name" isTrl="N" original="PrintPaymentsBPLanguageProcess">PrintPaymentsBPLanguageProcess</value>
    <value column="Description" isTrl="Y" original="Print Payments BP Language Process ">Imprime Pagos en el Lenguaje del Tercero </value>
    <value column="Help" isTrl="N" original=""/>
  </row>
  <row id="FF808181339321290133937B218500EC" trl="N">
    <value column="Name" isTrl="N" original="PrintShipmentsBPLanguageProcess">PrintShipmentsBPLanguageProcess</value>
    <value column="Description" isTrl="N" original="Print Shipments BP Language Process">Print Shipments BP Language Process</value>
    <value column="Help" isTrl="N" original=""/>
  </row>
</compiereTrl>
